scrz/__init__.py
scrz/__main__.py
scrz/binary/__init__.py
scrz/configuration.py
scrz/driver.py
scrz/extractor.py
scrz/font/10x18b.pil
scrz/font/10x18b.png
scrz/font/10x18n.pil
scrz/font/10x18n.png
scrz/font/10x20b.pil
scrz/font/10x20b.png
scrz/font/10x20n.pil
scrz/font/10x20n.png
scrz/font/11x22b.pil
scrz/font/11x22b.png
scrz/font/11x22n.pil
scrz/font/11x22n.png
scrz/font/12x24b.pil
scrz/font/12x24b.png
scrz/font/12x24n.pil
scrz/font/12x24n.png
scrz/font/14x28b.pil
scrz/font/14x28b.png
scrz/font/14x28n.pil
scrz/font/14x28n.png
scrz/font/16x32b.pil
scrz/font/16x32b.png
scrz/font/16x32n.pil
scrz/font/16x32n.png
scrz/font/6x12b.pil
scrz/font/6x12b.png
scrz/font/6x12n.pil
scrz/font/6x12n.png
scrz/font/8x14b.pil
scrz/font/8x14b.png
scrz/font/8x14n.pil
scrz/font/8x14n.png
scrz/font/8x16b.pil
scrz/font/8x16b.png
scrz/font/8x16n.pil
scrz/font/8x16n.png
scrz/font/__init__.py
scrz/format.py
scrz/generator.py
scrz/histogram.py
scrz/layout.py
scrz/progress.py
scrz/py.typed
scrz/renderer.py
scrz/scanner.py
scrz/swapper.py
scrz/tempfile.py
scrz/types.py
scrz/vignette.py
screenz-1.13.0.dist-info/METADATA
screenz-1.13.0.dist-info/WHEEL
screenz-1.13.0.dist-info/entry_points.txt
screenz-1.13.0.dist-info/RECORD
