Metadata-Version: 2.3
Name: screenz
Version: 1.13.0
Summary: ScreenZ
License: MIT
Author: deadmaster
Author-email: deadmaster@noreply.codeberg.org
Requires-Python: >=3.13,<4.0
Classifier: License :: OSI Approved :: MIT License
Classifier: Programming Language :: Python :: 3
Classifier: Programming Language :: Python :: 3.13
Classifier: Topic :: Multimedia :: Video
Requires-Dist: Pillow (>=11.2.1,<12.0.0)
Requires-Dist: colorama (>=0.4.6,<0.5.0) ; sys_platform == "win32"
Project-URL: Repository, https://codeberg.org/deadmaster/screenz
